{
  "gitSyncId": "6753170b470c7870d4338fa7_f9b8b598-c644-4fad-9333-f643e8bd8a94",
  "id": "auto_ModalMoreInformation.formatOffer",
  "pluginId": "js-plugin",
  "pluginType": "JS",
  "unpublishedAction": {
    "actionConfiguration": {
      "encodeParamsToggle": true,
      "jsArguments": [
        {
          "name": "offer"
        }
      ],
      "paginationType": "NONE",
      "timeoutInMillisecond": 10000
    },
    "collectionId": "auto_ModalMoreInformation",
    "confirmBeforeExecute": false,
    "datasource": {
      "isAutoGenerated": false,
      "name": "UNUSED_DATASOURCE",
      "pluginId": "js-plugin"
    },
    "dynamicBindingPathList": [
      {
        "key": "body"
      }
    ],
    "fullyQualifiedName": "ModalMoreInformation.formatOffer",
    "name": "formatOffer",
    "pageId": "auto",
    "runBehaviour": "MANUAL",
    "userSetOnLoad": false
  }
}