{
  "gitSyncId": "6753170b470c7870d4338fa7_f9e8b809-c483-45cd-8790-8b9055a800bb",
  "id": "health_SharedOffers.getSavingsUnit",
  "pluginId": "js-plugin",
  "pluginType": "JS",
  "unpublishedAction": {
    "actionConfiguration": {
      "encodeParamsToggle": true,
      "jsArguments": [
        {
          "name": "savings"
        }
      ],
      "paginationType": "NONE",
      "timeoutInMillisecond": 10000
    },
    "collectionId": "health_SharedOffers",
    "confirmBeforeExecute": false,
    "datasource": {
      "isAutoGenerated": false,
      "name": "UNUSED_DATASOURCE",
      "pluginId": "js-plugin"
    },
    "dynamicBindingPathList": [
      {
        "key": "body"
      }
    ],
    "fullyQualifiedName": "SharedOffers.getSavingsUnit",
    "name": "getSavingsUnit",
    "pageId": "health",
    "runBehaviour": "MANUAL",
    "userSetOnLoad": false
  }
}