{
  "gitSyncId": "6753170b470c7870d4338fa7_f4a1a7dd-a39b-4169-87e0-a024f0d35d96",
  "id": "health_ModalMoreInformation.getOptionValue",
  "pluginId": "js-plugin",
  "pluginType": "JS",
  "unpublishedAction": {
    "actionConfiguration": {
      "encodeParamsToggle": true,
      "jsArguments": [
        {
          "name": "option"
        }
      ],
      "paginationType": "NONE",
      "timeoutInMillisecond": 10000
    },
    "collectionId": "health_ModalMoreInformation",
    "confirmBeforeExecute": false,
    "datasource": {
      "isAutoGenerated": false,
      "name": "UNUSED_DATASOURCE",
      "pluginId": "js-plugin"
    },
    "dynamicBindingPathList": [
      {
        "key": "body"
      }
    ],
    "fullyQualifiedName": "ModalMoreInformation.getOptionValue",
    "name": "getOptionValue",
    "pageId": "health",
    "runBehaviour": "MANUAL",
    "userSetOnLoad": false
  }
}